pyobe/__VERSION__.py
pyobe/__init__.py
pyobe/logger.py
pyobe/probe.py
pyobe-0.0.9.dist-info/METADATA
pyobe-0.0.9.dist-info/WHEEL
pyobe-0.0.9.dist-info/top_level.txt
pyobe-0.0.9.dist-info/RECORD
