Metadata-Version: 2.1
Name: pyobe
Version: 0.0.9
Summary: Probe system for crawl data
Home-page: https://github.com/Jannchie/pyobe
Author: Jannchie
Author-email: jannchie@gmail.com
License: UNKNOWN
Platform: UNKNOWN
Classifier: Programming Language :: Python :: 3
Classifier: License :: OSI Approved :: MIT License
Classifier: Operating System :: OS Independent
Requires-Python: >=3.8
Requires-Dist: aiohttp
